{
  "title": "نشر روابط البث المباشر",
  "slug": "nshr-rwabt-albth-alm",
  "description": "روابط البث المباشر لأهم مباريات كرة القدم تُقدم للمشجعين لمتابعة الأحداث الرياضية الحية.",
  "category": "sports",
  "date": "2026-05-05",
  "time": "18:00",
  "updated": "2026-02-07",
  "image": "assets/images/1770478337379_IMG_٢٠٢٦٠٢٠٧_١٨٣٠٤٥.webp",
  "content": "{\n\"title\": \"بث مباشر لمباراة برشلونة ضد مايوركا بجودة عالية\",\n\"slug\": \"live-broadcast-barcelona-vs-majorka-high-quality\",\n\"description\": \"تتابع الجماهير مباراة برشلونة ومايوركا عبر البث المباشر بجودة عالية. روابط عديدة متاحة للمشاهدين.\",\n\"category\": \"sports\",\n\"tags\": [\"barcelona\",\"maiorca\",\"live broadcast\",\"football\",\"sports news\"],\n\"content\": \"البث المباشر لمباراة برشلونة ضد مايوركا بجودة عالية.\\n\\nتتابع الجماهير مباراة برشلونة ومايوركا عبر البث المباشر بجودة عالية. روابط متعددة تقدم خيارات متنوعة لمتابعة المباراة في مختلف الظروف.\\n\\n## روابط البث المباشر\\n\\n[الرابط الأول](https://www.facebook.com/share/v/1CLQsibha8/)\\nبث مباشر بجودة مستقرة.\\n\\n[الرابط الثاني](https://www.facebook.com/uiyuittu6/videos/1448865930205853/?mibextid=NnVzG8)\\nخيار بديل للضغط العالي.\\n\\n[الرابط الثالث](https://www.facebook.com/share/v/1CqXFsnv7R/)\\nبث احتياطي.\\n\\n[الرابط الرابع](https://www.facebook.com/share/v/18Gqbwudiv/)\\nجودة متوسطة.\\n\\n[الرابط الخامس](https://www.facebook.com/share/v/1AXaZLzRka/)\\nآخر خيار متاح في حال التعطل.\\n\\n## ملاحظات حول البث المباشر\\n\\nتحذير تقني: قد تواجه بعض الروابط تأخيرات أو انقطاعات في حال وجود ضغط كبير على الخوادم.\\n\\n## خلاصة\\n\\nهذه الروابط توفر تجربة مشاهدة مرنة وتتيح لمستخدميها التبديل بين خيارات مختلفة لضمان استمرار المتعة في المشاهدة.\"\n}",
  "youtubeVideoId": "",
  "summary": ""
}